pydotted/__init__.py
pydotted/pydotted.py
pydotted-0.0.8.dist-info/LICENSE.txt
pydotted-0.0.8.dist-info/METADATA
pydotted-0.0.8.dist-info/WHEEL
pydotted-0.0.8.dist-info/top_level.txt
pydotted-0.0.8.dist-info/RECORD
