Metadata-Version: 2.1
Name: pydotted
Version: 0.0.8
Summary: pydotted
Home-page: https://github.com/aredden/pydotted.git
Author: Alex Redden
Author-email: alexander.h.redden@gmail.com
License: MIT
Keywords: python,dict,dot,dotdict,dot notation,pydotted
Platform: UNKNOWN
Classifier: Development Status :: 3 - Alpha
Classifier: License :: OSI Approved :: MIT License
Classifier: Operating System :: OS Independent
Classifier: Topic :: Utilities
Classifier: Programming Language :: Python :: 3.6
Classifier: Programming Language :: Python :: 3.7
Classifier: Programming Language :: Python :: 3.8
Classifier: Programming Language :: Python :: 3.9
Classifier: Programming Language :: Python :: 3.10
Requires-Python: >=3.6
License-File: LICENSE.txt
